firecast/__init__.py
firecast/main.py
firecast/version.py
firecast/config/__init__.py
firecast/config/config.py
firecast/config/correlation_matrix.py
firecast/core/__init__.py
firecast/core/sequences_generator.py
firecast/core/simulation.py
firecast/core/simulation_state.py
firecast/reporting/__init__.py
firecast/reporting/console_report.py
firecast/reporting/graph_report.py
firecast/reporting/markdown_report.py
firecast/utils/__init__.py
firecast/utils/colors.py
firecast/utils/helpers.py
firecast-0.1.3.dist-info/licenses/LICENSE
firecast_data/__init__.py
firecast_data/daily-to-monthly.py
firecast_data/data_metrics.md
firecast_data/data_metrics.py
firecast_data/portfolios.md
firecast_data/portfolios.py
firecast_data/price_to_eur.py
firecast_data/analytics/__init__.py
firecast_data/analytics/analysis.py
firecast_data/analytics/optimization.py
firecast_data/analytics/plotting.py
firecast_data/data/MSCI-All-EUR-daily.xlsx
firecast_data/data/MSCI-All-EUR-monthly.xlsx
firecast_data/data/MSCI-All-USD-daily.xlsx
firecast_data/data/MSCI-All-USD-monthly.xlsx
firecast_data/data/shocks.md
firecast-0.1.3.dist-info/METADATA
firecast-0.1.3.dist-info/WHEEL
firecast-0.1.3.dist-info/entry_points.txt
firecast-0.1.3.dist-info/top_level.txt
firecast-0.1.3.dist-info/RECORD
