Metadata-Version: 2.4
Name: firecast
Version: 0.1.3
Summary: Monte Carlo simulation tool for FIRE (Financial Independence / Early Retirement) planning.
Author-email: aimer63 <63aimer@gmail.com>
License-Expression: AGPL-3.0-or-later
Requires-Python: >=3.10
License-File: LICENSE
Requires-Dist: numpy
Requires-Dist: pandas
Requires-Dist: pandas-stubs
Requires-Dist: openpyxl
Requires-Dist: PyQt5
Requires-Dist: matplotlib
Requires-Dist: seaborn
Requires-Dist: pydantic
Requires-Dist: tomli
Requires-Dist: tomli-w
Requires-Dist: tqdm
Provides-Extra: dev
Requires-Dist: pytest; extra == "dev"
Requires-Dist: coverage; extra == "dev"
Requires-Dist: twine; extra == "dev"
Requires-Dist: build; extra == "dev"
Requires-Dist: commitizen; extra == "dev"
Dynamic: license-file
